easyib/__init__.py
easyib/easyib.py
easyib-0.2.5.dist-info/LICENSE
easyib-0.2.5.dist-info/METADATA
easyib-0.2.5.dist-info/WHEEL
easyib-0.2.5.dist-info/top_level.txt
easyib-0.2.5.dist-info/RECORD
