Metadata-Version: 2.1
Name: easyib
Version: 0.2.5
Summary: Python wrapper for Interactive Brokers Client Portal Web API
Home-page: https://github.com/ashpipe/easyib
Author: ashpipe
Author-email: ashedpipe@gmail.com
Project-URL: Bug Tracker, https://github.com/ashpipe/easyib/issues
Keywords: REST,Interactive Brokers,Client Portal API
Classifier: Programming Language :: Python :: 3
Classifier: License :: OSI Approved :: BSD License
Classifier: Operating System :: OS Independent
Requires-Python: >=3.6
License-File: LICENSE
Requires-Dist: requests
Requires-Dist: urllib3
